opentracing_utils/__init__.py
opentracing_utils/common.py
opentracing_utils/decorators.py
opentracing_utils/span.py
opentracing_utils/tracers.py
opentracing_utils/libs/__init__.py
opentracing_utils/libs/_django.py
opentracing_utils/libs/_flask.py
opentracing_utils/libs/_requests.py
opentracing_utils/libs/_sqlalchemy.py
opentracing_utils/libs/aiohttp_.py
opentracing_utils-0.23.0.dist-info/DESCRIPTION.rst
opentracing_utils-0.23.0.dist-info/METADATA
opentracing_utils-0.23.0.dist-info/RECORD
opentracing_utils-0.23.0.dist-info/WHEEL
opentracing_utils-0.23.0.dist-info/metadata.json
opentracing_utils-0.23.0.dist-info/top_level.txt
tests/test_django/__init__.py
tests/test_django/manage.py
tests/test_django/settings.py
tests/test_django/test_django_middleware.py
tests/test_django/urls.py
tests/test_django/app/__init__.py
tests/test_django/app/views.py
