Metadata-Version: 2.0
Name: opentracing-utils
Version: 0.23.0
Summary: OpenTracing utilities library
Home-page: https://github.com/zalando-zmon/opentracing-utils
License: The MIT License (MIT)
Platform: UNKNOWN
Classifier: Development Status :: 4 - Beta
Classifier: Intended Audience :: Developers
Classifier: License :: OSI Approved :: MIT License
Classifier: Programming Language :: Python :: 2.7
Classifier: Programming Language :: Python :: 3.4
Classifier: Programming Language :: Python :: 3.5
Classifier: Programming Language :: Python :: 3.6
Classifier: Programming Language :: Python
Classifier: Programming Language :: Python :: Implementation :: CPython
Classifier: Environment :: Console
Classifier: Operating System :: POSIX :: Linux
Classifier: Operating System :: MacOS :: MacOS X
Classifier: Topic :: Utilities
Classifier: Topic :: System :: Monitoring
Classifier: Topic :: System :: Networking :: Monitoring
License-File: LICENSE
Requires-Dist: future
Requires-Dist: opentracing
